xmatch/__init__.py
xmatch/xmatch.py
xmatch-0.1.1.dist-info/DESCRIPTION.rst
xmatch-0.1.1.dist-info/METADATA
xmatch-0.1.1.dist-info/RECORD
xmatch-0.1.1.dist-info/WHEEL
xmatch-0.1.1.dist-info/entry_points.txt
xmatch-0.1.1.dist-info/metadata.json
xmatch-0.1.1.dist-info/top_level.txt
