Metadata-Version: 2.0
Name: xmatch
Version: 0.1.1
Summary: Cross correlation of several catalog at once
Home-page: https://git.ias.u-psud.fr/abeelen/xmatch
Author: Alexandre Beelen, Marian Douspis
Author-email: alexandre.beelen@ias.u-psud.fr
License: LGPL-3.0+
Download-URL: https://git.ias.u-psud.fr/abeelen/xmatch/repository/archive.tar.gz?0.1.1
Platform: UNKNOWN
Classifier: Programming Language :: Python :: 2.7
Classifier: Programming Language :: Python :: 3.5
Classifier: Topic :: Scientific/Engineering :: Astronomy
Classifier: Intended Audience :: Science/Research
Classifier: License :: OSI Approved :: GNU Lesser General Public License v3 or later (LGPLv3+)
Requires-Dist: astropy (>=1.2)
Requires-Dist: astroquery (>=0.3.3)
Requires-Dist: numpy (>=1.11)
